parserBI/__init__.py
parserBI/classes.py
parserBI/example.py
parserBI-0.0.3.dist-info/LICENSE
parserBI-0.0.3.dist-info/METADATA
parserBI-0.0.3.dist-info/WHEEL
parserBI-0.0.3.dist-info/entry_points.txt
parserBI-0.0.3.dist-info/top_level.txt
parserBI-0.0.3.dist-info/RECORD
